modul_a.py
my_pyqt_gui.py
mein_super_cooles_demo_project-0.0.1.dist-info/METADATA
mein_super_cooles_demo_project-0.0.1.dist-info/WHEEL
mein_super_cooles_demo_project-0.0.1.dist-info/top_level.txt
mein_super_cooles_demo_project-0.0.1.dist-info/RECORD
