Metadata-Version: 2.4
Name: mein_super_cooles_demo_project
Version: 0.0.1
Summary: Demonstration eines PyPI Uploads
Author-email: Thomas Benkenstein <thomas.benkenstein@experteach.de>
Classifier: Development Status :: 1 - Planning
Classifier: Operating System :: Microsoft :: Windows :: Windows 11
Classifier: Environment :: X11 Applications :: Qt
Requires-Python: >=3.12
Requires-Dist: pyqt5
Requires-Dist: numpy
